staticinline/__init__.py
staticinline/apps.py
staticinline/main.py
staticinline/templatetags/__init__.py
staticinline/templatetags/staticinline.py
staticinline/tests/__init__.py
staticinline/tests/test_read_data.py
staticinline/tests/test_templatetag.py
staticinline/tests/testapp/__init__.py
staticinline/tests/testapp/apps.py
staticinline/tests/testapp/settings.py
staticinline/tests/testapp/static/testapp/myfile.js
django_staticinline-1.6.dist-info/METADATA
django_staticinline-1.6.dist-info/WHEEL
django_staticinline-1.6.dist-info/RECORD
