Metadata-Version: 2.1
Name: django-staticinline
Version: 1.6
Summary: Django template tag to load static files inline with your template.
Home-page: https://github.com/bartTC/django-staticinline
License: MIT
Keywords: django,staticfiles,inline,performance
Author: Martin Mahner
Author-email: martin@mahner.org
Requires-Python: >=3.9,<4.0
Classifier: Development Status :: 5 - Production/Stable
Classifier: Environment :: Web Environment
Classifier: Framework :: Django
Classifier: Intended Audience :: Developers
Classifier: License :: OSI Approved :: MIT License
Classifier: Operating System :: OS Independent
Classifier: Programming Language :: Python
Classifier: Programming Language :: Python :: 3
Classifier: Programming Language :: Python :: 3.9
Classifier: Programming Language :: Python :: 3.10
Classifier: Programming Language :: Python :: 3.11
Classifier: Programming Language :: Python :: 3.12
Classifier: Programming Language :: Python :: 3.13
Requires-Dist: django (>=3.2)
Project-URL: Bugtracker, https://github.com/bartTC/django-staticinline/issues
Project-URL: Source, https://github.com/bartTC/django-staticinline
